buzz/__init__.py
buzz/base.py
buzz/py.typed
buzz/tools.py
buzz_demo/__init__.py
buzz_demo/check_expressions.py
buzz_demo/enforce_defined.py
buzz_demo/ensure_type.py
buzz_demo/handle_errors.py
buzz_demo/helpers.py
buzz_demo/main.py
buzz_demo/require_condition.py
buzz_demo/using_exc_builder.py
buzz_demo/with_buzz_class.py
py_buzz-7.3.0.dist-info/METADATA
py_buzz-7.3.0.dist-info/WHEEL
py_buzz-7.3.0.dist-info/entry_points.txt
py_buzz-7.3.0.dist-info/licenses/LICENSE.md
py_buzz-7.3.0.dist-info/RECORD
