Metadata-Version: 2.4
Name: py-buzz
Version: 7.3.0
Summary: "That's not flying, it's falling with style": Exceptions with extras
Project-URL: homepage, https://dusktreader.github.io/py-buzz/
Project-URL: source, https://github.com/dusktreader/py-buzz
Project-URL: changelog, https://github.com/dusktreader/py-buzz/blob/main/CHANGELOG.md
Author-email: Tucker Beck <tucker.beck@gmail.com>
License-File: LICENSE.md
Requires-Python: >=3.9
Provides-Extra: demo
Requires-Dist: auto-name-enum>=2.0.0; extra == 'demo'
Requires-Dist: rich>=13.9.4; extra == 'demo'
Requires-Dist: snick>=1.4.1; extra == 'demo'
Requires-Dist: typer>=0.15.2; extra == 'demo'
